simple_flask_captcha_k_fork/__init__.py
simple_flask_captcha_k_fork/config.py
flask_simple_captcha_k_fork-1.1.3.dist-info/LICENSE.txt
flask_simple_captcha_k_fork-1.1.3.dist-info/METADATA
flask_simple_captcha_k_fork-1.1.3.dist-info/WHEEL
flask_simple_captcha_k_fork-1.1.3.dist-info/top_level.txt
flask_simple_captcha_k_fork-1.1.3.dist-info/RECORD
