Metadata-Version: 2.1
Name: flask-simple-captcha-k-fork
Version: 1.1.3
Summary: Extremely simple, "Good Enough" captcha implemention for flask forms. No server side sessions required.
Home-page: https://github.com/khancerberus/flask-simple-captcha-k-fork
Author: Cary Carter / Fork: khancerberus
Author-email: vi.valenzuelam@gmail.com
License: MIT
Classifier: License :: OSI Approved :: MIT License
Classifier: Programming Language :: Python :: 3
Classifier: Programming Language :: Python :: 3.7
License-File: LICENSE.txt
Requires-Dist: Werkzeug (>=0.16.0)
Requires-Dist: Pillow (>=6.1.0)
Requires-Dist: MarkupSafe (>=2.1.1)
